bobifi/__init__.py
bobifi/data/samtrafiken-prod.json
bobifi/data/samtrafiken-test.json
bobifi/samtrafiken.py
bobifi/utils.py
bobifi-2024.11.25.dist-info/LICENSE
bobifi-2024.11.25.dist-info/METADATA
bobifi-2024.11.25.dist-info/WHEEL
bobifi-2024.11.25.dist-info/RECORD
