Metadata-Version: 2.1
Name: bobifi
Version: 2024.11.25
Summary: BoB Metadata Keys and URLs
Home-page: https://github.com/bobcat-ticketing/python-bobifi'
License: BSD-2-Clause
Author: Jakob Schlyter
Author-email: jakob@kirei.se
Requires-Python: >=3.9,<4.0
Classifier: License :: OSI Approved :: BSD License
Classifier: Programming Language :: Python :: 3
Classifier: Programming Language :: Python :: 3.9
Classifier: Programming Language :: Python :: 3.10
Classifier: Programming Language :: Python :: 3.11
Classifier: Programming Language :: Python :: 3.12
Classifier: Programming Language :: Python :: 3.13
Project-URL: Repository, https://github.com/bobcat-ticketing/python-bobifi'
